ricksay/__init__.py
ricksay/argparser.py
ricksay/backend.py
ricksay/balloon.py
ricksay/colourstack.py
ricksay/common.py
ricksay/kms.py
ricksay/lists.py
ricksay/main.py
ricksay/metadata.py
ricksay/ponysay.py
ricksay/ponysaytool.py
ricksay/spellocorrecter.py
ricksay/ucs.py
ricksay/balloons/ascii.say
ricksay/balloons/cowsay.say
ricksay/balloons/linux-vt.say
ricksay/balloons/round.say
ricksay/balloons/unicode.say
ricksay/ponies/Beth/95570.pony
ricksay/ponies/Beth/95571.pony
ricksay/ponies/Beth/95572.pony
ricksay/ponies/Beth/95573.pony
ricksay/ponies/Beth/95574.pony
ricksay/ponies/Jerry/75682.pony
ricksay/ponies/Jerry/95297.pony
ricksay/ponies/Jerry/95298.pony
ricksay/ponies/Jerry/95328.pony
ricksay/ponies/Jerry/95504.pony
ricksay/ponies/Jerry/95569.pony
ricksay/ponies/Jerry/96069.pony
ricksay/ponies/Jerry/96070.pony
ricksay/ponies/Jerry/96071.pony
ricksay/ponies/Jerry/96072.pony
ricksay/ponies/Jerry/96073.pony
ricksay/ponies/Jerry/97109.pony
ricksay/ponies/Jerry/97110.pony
ricksay/ponies/Jerry/97111.pony
ricksay/ponies/Jerry/97112.pony
ricksay/ponies/Morty/75530.pony
ricksay/ponies/Morty/75531.pony
ricksay/ponies/Morty/75532.pony
ricksay/ponies/Morty/75533.pony
ricksay/ponies/Morty/75534.pony
ricksay/ponies/Morty/75535.pony
ricksay/ponies/Morty/75536.pony
ricksay/ponies/Morty/75537.pony
ricksay/ponies/Morty/75538.pony
ricksay/ponies/Morty/75539.pony
ricksay/ponies/Morty/75540.pony
ricksay/ponies/Morty/75541.pony
ricksay/ponies/Morty/75542.pony
ricksay/ponies/Morty/75543.pony
ricksay/ponies/Morty/75544.pony
ricksay/ponies/Morty/75545.pony
ricksay/ponies/Morty/75546.pony
ricksay/ponies/Morty/75547.pony
ricksay/ponies/Morty/75548.pony
ricksay/ponies/Morty/75549.pony
ricksay/ponies/Morty/75550.pony
ricksay/ponies/Morty/75551.pony
ricksay/ponies/Morty/75552.pony
ricksay/ponies/Morty/75553.pony
ricksay/ponies/Morty/75554.pony
ricksay/ponies/Morty/75555.pony
ricksay/ponies/Morty/75556.pony
ricksay/ponies/Morty/75557.pony
ricksay/ponies/Morty/75558.pony
ricksay-0.2.6.dist-info/LICENSE.txt
ricksay-0.2.6.dist-info/METADATA
ricksay-0.2.6.dist-info/WHEEL
ricksay-0.2.6.dist-info/top_level.txt
ricksay-0.2.6.dist-info/RECORD
