Metadata-Version: 2.1
Name: ricksay
Version: 0.2.6
Summary: Rick & Morty quotes of the day with ponies included!
Home-page: https://github.com/roma-guru/ricksay
Author: Roman Voropaev
Author-email: voropaev.roma@gmail.com
License: BSD
Platform: UNKNOWN
Classifier: Environment :: Console
Classifier: Development Status :: 4 - Beta
Classifier: License :: OSI Approved :: BSD License
Classifier: Programming Language :: Python
Classifier: Programming Language :: Python :: 3
Classifier: Operating System :: Unix
Classifier: Topic :: Games/Entertainment :: Fortune Cookies
Requires-Python: >=3.0.0
License-File: LICENSE.txt
Requires-Dist: click (==7.*)
